dracon_types/v1/engine.proto
dracon_types/v1/engine_pb2.py
dracon_types/v1/engine_pb2.pyi
dracon_types/v1/issue.proto
dracon_types/v1/issue_pb2.py
dracon_types/v1/issue_pb2.pyi
dracon_types-0.0.1.dist-info/METADATA
dracon_types-0.0.1.dist-info/WHEEL
dracon_types-0.0.1.dist-info/RECORD
